.coveragerc
CHANGES.rst
LICENSE.txt
MANIFEST.in
README.rst
development.ini
i18n.sh
requirements.txt
rtd.txt
setup.cfg
setup.py
kotti_backend/__init__.py
kotti_backend/populate.py
kotti_backend/security.py
kotti_backend.egg-info/PKG-INFO
kotti_backend.egg-info/SOURCES.txt
kotti_backend.egg-info/dependency_links.txt
kotti_backend.egg-info/not-zip-safe
kotti_backend.egg-info/requires.txt
kotti_backend.egg-info/top_level.txt
kotti_backend/locale/kotti_backend.pot
kotti_backend/locale/en/LC_MESSAGES/kotti_backend.mo
kotti_backend/locale/en/LC_MESSAGES/kotti_backend.po
kotti_backend/locale/it/LC_MESSAGES/kotti_backend.mo
kotti_backend/locale/it/LC_MESSAGES/kotti_backend.po
kotti_backend/tests/conftest.py
kotti_backend/tests/test_default_permission.py
kotti_backend/tests/test_goto_frontend.py
kotti_backend/tests/test_populate.py
kotti_backend/tests/test_security.py
kotti_backend/tests/test_views.py
kotti_backend/tests/test_workflow.py
kotti_backend/views/__init__.py
kotti_backend/views/goto_frontend.py
kotti_backend/views/override_root_view.py
kotti_backend/workflows/private_workflow.zcml
kotti_backend/workflows/simple_backend.zcml