Metadata-Version: 1.1
Name: kotti-backend
Version: 0.2.0
Summary: Turns Kotti CMS into a private content administration area
Home-page: https://github.com/Kotti/kotti_backend
Author: Kotti developers
Author-email: kotti@googlegroups.com
License: BSD-derived (http://www.repoze.org/LICENSE.txt)
Keywords: kotti web cms wcms pylons pyramid sqlalchemy bootstrap
Platform: UNKNOWN
Classifier: Programming Language :: Python
Classifier: Programming Language :: Python :: 2.6
Classifier: Programming Language :: Python :: 2.7
Classifier: Framework :: Pylons
Classifier: Topic :: Internet :: WWW/HTTP
Classifier: Topic :: Internet :: WWW/HTTP :: Dynamic Content
Classifier: Topic :: Internet :: WWW/HTTP :: WSGI :: Application
Classifier: License :: Repoze Public License
